{
    "all_week": false,
    "description": "A walk to explore Raymond Unwin's aspirations to create a new form of town extension which encompassed the best aspects of town and country. Run by David Davidson of the Hampstead Garden Suburb Trust. \r\n\r\n2 of 3 tours run by the Trust.",
    "design": {
        "designers": [
            {
                "architect": "Unwin & Parker",
                "description": null,
                "year": "1907"
            },
            {
                "architect": "Lutyens",
                "description": null,
                "year": "1907"
            },
            {
                "architect": "Bunney",
                "description": null,
                "year": "1907"
            },
            {
                "architect": "Baillie Scott and others",
                "description": null,
                "year": "1907"
            }
        ],
        "periods": [
            "Lutyens",
            "Bunney",
            "Baillie Scott and others",
            "Edwardian"
        ],
        "types": [
            "walk/tour"
        ]
    },
    "events": [],
    "facilities": [],
    "factsheet": [
        {
            "heading": "The Sharing of Great Things",
            "paragraphs": [
                "A walking tour exploring the older part of Hampstead Garden Suburb,  which is a planned community founded in 1907 by the social reformer Henrietta Barnett. The community was built in a largely Arts & Crafts style with a great emphasis on the townscape as a whole rather than individual buildings."
            ]
        }
    ],
    "id": 11774,
    "images": [
        {
            "archive_url": "https://raw.githubusercontent.com/Jonty/open-house-london-images/master/images/2024/11774/building_11774_0_e6526a1165bf0661f3f3c1208cc5c369.jpg",
            "description": null,
            "title": "Erskine Hill",
            "url": "https://d25hwkr75zzfa.cloudfront.net/store/photo/large/building_11774_0_e6526a1165bf0661f3f3c1208cc5c369.jpg"
        }
    ],
    "links": [],
    "location": {
        "address": "The Old Bull and Bush, North End Way, NW3 7HE",
        "latitude": 51.5675144,
        "longitude": -0.1826116,
        "meeting_point": null,
        "travel_info": [
            "Tube: Golders Green",
            "Additional travel info: Start outside the Old Bull and Bush (nearest station Golders Green tube); end at Temple Fortune House (Finchley Road)."
        ]
    },
    "name": "The Sharing of Great Things",
    "new_venue_this_year": false,
    "original_url": "https://programme.openhouse.org.uk/listings/11774",
    "ticketed_events": false
}