{
    "all_week": false,
    "balloted_events": false,
    "description": "Housed in an industrial 50s warehouse formerly occupied by Rolls Royce and acquired in a semi-derelict state, its transformation was approached by the artist Henry Krokatsis as a large sculptural work. It has been constructed using found and redundant materials, balancing functionality and subversion. It continues to act as an evolving social sculpture.",
    "design": {
        "designers": [
            {
                "architect": "interior Henry Krokatsis",
                "description": null,
                "year": "1950"
            },
            {
                "architect": "exterior unkown",
                "description": null,
                "year": "1950"
            }
        ],
        "periods": [
            "exterior unkown",
            "Post-war"
        ],
        "types": [
            "art studio"
        ]
    },
    "events": [
        {
            "activity_type": "Drop in",
            "all_day": false,
            "balloted": false,
            "booking_link": null,
            "capacity": null,
            "date": "2025-09-13",
            "drop_in": true,
            "end": "2025-09-13T18:00:00+01:00",
            "fully_booked": false,
            "name": "Drop in: Justine Simons Open House Collection",
            "notes": "",
            "start": "2025-09-13T11:00:00+01:00",
            "ticketed": false
        },
        {
            "activity_type": "Drop in",
            "all_day": false,
            "balloted": false,
            "booking_link": null,
            "capacity": null,
            "date": "2025-09-14",
            "drop_in": true,
            "end": "2025-09-14T18:00:00+01:00",
            "fully_booked": false,
            "name": "Drop in: Justine Simons Open House Collection",
            "notes": "Please let us know if you plan to visit. Doing so allows\n                    the venue to plan ahead and you will be notified by email\n                    about any changes to the programme that might affect your\n                    visit.",
            "start": "2025-09-14T11:00:00+01:00",
            "ticketed": false
        }
    ],
    "facilities": [
        "Drinking water",
        "Gender neutral toilet",
        "Seating available",
        "Toilets"
    ],
    "factsheet": [
        {
            "heading": "Background",
            "paragraphs": [
                "Housed in an industrial 50s warehouse formerly occupied by Rolls Royce and acquired in a semi-derelict state, its transformation was approached by the artist Henry Krokatsis as a large evolving sculptural work. It has been constructed using found and redundant materials, balancing functionality and subversion. The 12,000 sq ft space currently houses a not-for-profit project space and a 1000 sq ft roof terrace and event space. There are 22 purpose-built artists’ studios across 2 floors. This unfolding social sculpture continues to act as a source of inspiration, enquiry, and experimentation."
            ]
        }
    ],
    "first_published": "2025-08-21T16:19:24.532588",
    "id": 12837,
    "images": [
        {
            "archive_url": "https://raw.githubusercontent.com/infrastructureclub/open-house-london-images/master/images/2025/12837/building_12837_16-low-res-end-copy_b8dcfc7a5918c6bd6b8f9d3cbbe70057.jpg",
            "description": null,
            "title": "Queensrollahouse interior",
            "url": "https://d25hwkr75zzfa.cloudfront.net/store/photo/large/building_12837_16-low-res-end-copy_b8dcfc7a5918c6bd6b8f9d3cbbe70057.jpg"
        },
        {
            "archive_url": "https://raw.githubusercontent.com/infrastructureclub/open-house-london-images/master/images/2025/12837/building_12837_queensrollahouse-groundfloor-atrium-2_f32232ca47de6ec32aa73b3bec5bf087.jpg",
            "description": null,
            "title": "Queensrollahouse interior",
            "url": "https://d25hwkr75zzfa.cloudfront.net/store/photo/large/building_12837_queensrollahouse-groundfloor-atrium-2_f32232ca47de6ec32aa73b3bec5bf087.jpg"
        },
        {
            "archive_url": "https://raw.githubusercontent.com/infrastructureclub/open-house-london-images/master/images/2025/12837/building_12837_queensrollahouse-groundfloor-atrium-3_75ad034216ed71fc2f5072281065abdf.jpg",
            "description": null,
            "title": "Queensrollahouse interior",
            "url": "https://d25hwkr75zzfa.cloudfront.net/store/photo/large/building_12837_queensrollahouse-groundfloor-atrium-3_75ad034216ed71fc2f5072281065abdf.jpg"
        },
        {
            "archive_url": "https://raw.githubusercontent.com/infrastructureclub/open-house-london-images/master/images/2025/12837/building_12837_queensrollahouse-roofterrace-1_6000_50a0d80d9e742d29de90202be6d4a08f.jpg",
            "description": null,
            "title": "Queensrollahouse roof terrace",
            "url": "https://d25hwkr75zzfa.cloudfront.net/store/photo/large/building_12837_queensrollahouse-roofterrace-1_6000_50a0d80d9e742d29de90202be6d4a08f.jpg"
        },
        {
            "archive_url": "https://raw.githubusercontent.com/infrastructureclub/open-house-london-images/master/images/2025/12837/building_12837_queensrollahouse-roofterrace-4_6000_26ca5e4690ff6dc6f05c39d0183230f3.jpg",
            "description": null,
            "title": "Queensrollahouse roof terrace",
            "url": "https://d25hwkr75zzfa.cloudfront.net/store/photo/large/building_12837_queensrollahouse-roofterrace-4_6000_26ca5e4690ff6dc6f05c39d0183230f3.jpg"
        },
        {
            "archive_url": "https://raw.githubusercontent.com/infrastructureclub/open-house-london-images/master/images/2025/12837/building_12837_queensrollahouse-exterior_94ca9e442e4ff643e4b8cc527bcfacc8.jpg",
            "description": null,
            "title": "Queensrollahouse exterior",
            "url": "https://d25hwkr75zzfa.cloudfront.net/store/photo/large/building_12837_queensrollahouse-exterior_94ca9e442e4ff643e4b8cc527bcfacc8.jpg"
        },
        {
            "archive_url": "https://raw.githubusercontent.com/infrastructureclub/open-house-london-images/master/images/2025/12837/building_12837_extdscf5969_edit_01a98462c6314074f4570839a6070a14.jpg",
            "description": null,
            "title": null,
            "url": "https://d25hwkr75zzfa.cloudfront.net/store/photo/large/building_12837_extdscf5969_edit_01a98462c6314074f4570839a6070a14.jpg"
        }
    ],
    "links": [
        {
            "href": "https://queensrollahouse.com",
            "title": "queensrollahouse.com"
        },
        {
            "href": "https://www.instagram.com/queensrollahouse/",
            "title": "www.instagram.com/queensrollahouse"
        }
    ],
    "location": {
        "address": "18 Trading Estate Road, NW10 7LU",
        "latitude": 51.52641,
        "longitude": -0.26931,
        "meeting_point": null,
        "travel_info": [
            "Tube: North Acton",
            "Train: Harlesden",
            "Bus: 187, 260, 487"
        ]
    },
    "name": "Queensrollahouse",
    "new_venue_this_year": false,
    "original_url": "https://programme.openhouse.org.uk/listings/12837",
    "ticketed_events": false,
    "venue_years_listed": [
        2024,
        2025
    ]
}