{
    "all_week": false,
    "balloted_events": false,
    "description": "Culture House is the first permanent exhibition space for Somali artefacts curated by the Somali community.",
    "design": {
        "designers": [
            {
                "architect": "Freehaus Design",
                "description": null,
                "year": "1"
            }
        ],
        "periods": [],
        "types": [
            "community/cultural"
        ]
    },
    "events": [],
    "facilities": [
        "Accessible toilet",
        "Drinking water",
        "Family-friendly event",
        "Large print guides",
        "Seating available",
        "Step-free routes",
        "Toilets"
    ],
    "factsheet": [
        {
            "heading": "Vision Statement",
            "paragraphs": [
                "The mission of the Culture Space is to showcase, collect, preserve, teach and promote knowledge and appreciation of the rich and diverse culture of the black African and Caribbean communities in London.",
                "We currently engage and serve participants of various ages, interests, and walks of life through educational programmes, communal and public dialogue, exhibitions, poetry, events spaces, creative co-working spaces, and other initiatives.",
                "Culture Space will offer the following:",
                "Culture space is a community space with options for co-working and for hiring for community events, exhibitions and cultural events. \nCreative place with classes, activities, and programmes run in collaboration with community partners using our space, exhibition hall, and gallery space.\nResource space: This is a repository of resources on Somali heritage, including printed and audio-visual materials (e.g., oral history recordings) and non-fragile heritage assets that the public can safely handle.\nLearning space: We will offer heritage lectures, demonstrations, workshops, readings (poetry and prose), oral history presentations, and intergenerational storytelling between older and younger using heritage as a means to cross the generational divide."
            ]
        }
    ],
    "first_published": "2025-07-22T21:24:20.000000",
    "id": 13159,
    "images": [
        {
            "archive_url": "https://raw.githubusercontent.com/infrastructureclub/open-house-london-images/master/images/2025/13159/building_13159_heritage_2daee79bbb0d7d0182365abe5e66eccc.jpg",
            "description": null,
            "title": null,
            "url": "https://d25hwkr75zzfa.cloudfront.net/store/photo/large/building_13159_heritage_2daee79bbb0d7d0182365abe5e66eccc.jpg"
        },
        {
            "archive_url": "https://raw.githubusercontent.com/infrastructureclub/open-house-london-images/master/images/2025/13159/building_13159_threadsofmemory_15a77b3524eefaf5734c890734342e7a.jpg",
            "description": null,
            "title": null,
            "url": "https://d25hwkr75zzfa.cloudfront.net/store/photo/large/building_13159_threadsofmemory_15a77b3524eefaf5734c890734342e7a.jpg"
        }
    ],
    "links": [
        {
            "href": "https://culturehouse.org.uk",
            "title": "culturehouse.org.uk"
        },
        {
            "href": "https://www.instagram.com/culturehouseorg/",
            "title": "www.instagram.com/culturehouseorg"
        }
    ],
    "location": {
        "address": "5A, Uxbridge Road, W12 8LJ",
        "latitude": 51.50508,
        "longitude": -0.22558,
        "meeting_point": null,
        "travel_info": [
            "Tube: Shepherd's Bush, Shepherd's Bush Market",
            "Train: Shepherd's Bush",
            "Bus: 207"
        ]
    },
    "name": "Culture House",
    "new_venue_this_year": true,
    "original_url": "https://programme.openhouse.org.uk/listings/13159",
    "ticketed_events": false,
    "venue_years_listed": [
        2025
    ]
}