{
    "all_week": false,
    "description": "An  exhibtion exploring 13 stories of  Enfield's cultural heritage - ranging from the first-generation Bangladeshi's through to London' s only vineyard and the poetry of Stevie Smith in Palmers Green.",
    "design": {
        "designers": [
            {
                "architect": "n/a",
                "description": null,
                "year": "0"
            }
        ],
        "periods": [
            "Contemporary"
        ],
        "types": [
            "community/cultural",
            "art in the public realm",
            "event"
        ]
    },
    "events": [],
    "facilities": [
        "Toilets",
        "Disabled access"
    ],
    "factsheet": [
        {
            "heading": "Explanation",
            "paragraphs": [
                "These  projects or ‘stories’ explore diverse elements of Enfield’s cultural heritage. These stories range from the lost Tudor palace of Elysng and the exquisite 19th century Arts and Crafts windows of Christ Church Southgate though to Bangladeshi migration to Enfield and the life of renowned Palmers Green poet Stevie Smith.",
                "All stories were developed and delivered in-between September 2021 and are ongoing until November 2022 by community organisations from across the borough – we hope you enjoy reading about them."
            ]
        }
    ],
    "id": 10956,
    "images": [
        {
            "archive_url": "https://raw.githubusercontent.com/infrastructureclub/open-house-london-images/master/images/2022/10956/building_10956_river-lea-ponders-end-1907_84fb1e96f318d915e62f1903db44bd2a.jpg",
            "description": null,
            "title": "River Lea Ponders End",
            "url": "https://d25hwkr75zzfa.cloudfront.net/store/photo/large/building_10956_river-lea-ponders-end-1907_84fb1e96f318d915e62f1903db44bd2a.jpg"
        },
        {
            "archive_url": "https://raw.githubusercontent.com/infrastructureclub/open-house-london-images/master/images/2022/10956/building_10956_christchurch-southgate_049973f369cc7665bb4fa6cd42255d8f.jpg",
            "description": null,
            "title": "ChristChurch Southgate Windows",
            "url": "https://d25hwkr75zzfa.cloudfront.net/store/photo/large/building_10956_christchurch-southgate_049973f369cc7665bb4fa6cd42255d8f.jpg"
        },
        {
            "archive_url": "https://raw.githubusercontent.com/infrastructureclub/open-house-london-images/master/images/2022/10956/building_10956_boxing-bishop_faa36253bac093ccd8f09beb2037b1c8.jpg",
            "description": null,
            "title": "Boxing Bishop",
            "url": "https://d25hwkr75zzfa.cloudfront.net/store/photo/large/building_10956_boxing-bishop_faa36253bac093ccd8f09beb2037b1c8.jpg"
        },
        {
            "archive_url": "https://raw.githubusercontent.com/infrastructureclub/open-house-london-images/master/images/2022/10956/building_10956_screenshot-2022-08-09-at-17-27-36_b424629806c95e876dc25010b56c1bd9.png",
            "description": null,
            "title": "",
            "url": "https://d25hwkr75zzfa.cloudfront.net/store/photo/large/building_10956_screenshot-2022-08-09-at-17-27-36_b424629806c95e876dc25010b56c1bd9.png"
        }
    ],
    "links": [],
    "location": {
        "address": "62 Smythe Cl , N9 0TZ",
        "latitude": 51.624319,
        "longitude": -0.0579953,
        "meeting_point": null,
        "travel_info": [
            "Train: Edmonton Green"
        ]
    },
    "name": "Stories of Enfield Travelling Exhibition",
    "original_url": "https://programme.openhouse.org.uk/listings/10956",
    "ticketed_events": false
}